rfb_battery_cycler/___version__.py
rfb_battery_cycler/app/app_man/__init__.py
rfb_battery_cycler/app/app_man/app_man_core.py
rfb_battery_cycler/app/app_man/app_man_node.py
rfb_battery_cycler/app/app_man/context.py
rfb_battery_cycler/mid/mid_dabs/__init__.py
rfb_battery_cycler/mid/mid_dabs/context.py
rfb_battery_cycler/mid/mid_dabs/mid_dabs.py
rfb_battery_cycler/mid/mid_meas/__init__.py
rfb_battery_cycler/mid/mid_meas/context.py
rfb_battery_cycler/mid/mid_meas/mid_meas.py
rfb_battery_cycler/mid/mid_pwr/__init__.py
rfb_battery_cycler/mid/mid_pwr/mid_pwr.py
rfb_battery_cycler/mid/mid_str/__init__.py
rfb_battery_cycler/mid/mid_str/context.py
rfb_battery_cycler/mid/mid_str/mid_str_cmd.py
rfb_battery_cycler/mid/mid_str/mid_str_facade.py
rfb_battery_cycler/mid/mid_str/mid_str_mapping.py
rfb_battery_cycler/mid/mid_str/mid_str_node.py
rfb_battery_cycler-0.0.2.dist-info/LICENSE.txt
rfb_battery_cycler-0.0.2.dist-info/METADATA
rfb_battery_cycler-0.0.2.dist-info/WHEEL
rfb_battery_cycler-0.0.2.dist-info/top_level.txt
rfb_battery_cycler-0.0.2.dist-info/RECORD
