Metadata-Version: 2.1
Name: rfb-battery-cycler
Version: 0.0.2
Summary: Battery cycler control used to execute custom profile on multiple battery technologies.
Author-email: Raldea <r.aldea.csic+pypi@gmail.com>, Javier Sanz <javiersanzmoline@gmail.com>, Marius Crisan <mariuscrsn+pypi@gmail.com>, Pablo Pastor <pastorpflores+pypi@gmail.com>, Luis Roche <luis.roche@hotmail.com>
License: GNU GENERAL PUBLIC LICENSE
Project-URL: Homepage, https://github.com/GIDEF-RFB/Battery-Cycler-Controller
Project-URL: Bug Reports, https://github.com/GIDEF-RFB/Battery-Cycler-Controller/issues
Project-URL: Bug Tracker, https://github.com/GIDEF-RFB/Battery-Cycler-Controller/issues
Project-URL: Source, https://github.com/GIDEF-RFB/Battery-Cycler-Controller/code/cycler/
Project-URL: Funding, https://donate.pypi.org
Keywords: Embedded Systems,Power Control,Lithium Battery Cycler,Battery,Industrial Battery,SoH,State of Health,SoC,State of Charge,Redox Flow Vanadium,Battery,Cycler,Battery Profiling
Classifier: Development Status :: 3 - Alpha
Classifier: Topic :: Software Development :: Embedded Systems
Classifier: Topic :: Database
Classifier: Topic :: File Formats :: JSON
Classifier: Topic :: Internet :: Log Analysis
Classifier: Topic :: Software Development :: Libraries :: Python Modules
Classifier: Topic :: System :: Hardware :: Hardware Drivers
Classifier: Topic :: System :: Networking :: Monitoring :: Hardware Watchdog
Classifier: Topic :: System :: Power (UPS)
Classifier: Operating System :: OS Independent
Classifier: License :: OSI Approved :: GNU Affero General Public License v3
Classifier: Programming Language :: Python :: 3
Classifier: Programming Language :: Python :: 3.7
Classifier: Programming Language :: Python :: 3.8
Classifier: Programming Language :: Python :: 3.9
Classifier: Programming Language :: Python :: 3.10
Classifier: Programming Language :: Python :: 3 :: Only
Classifier: Programming Language :: SQL
Classifier: Programming Language :: Unix Shell
Requires-Python: >=3.7
License-File: LICENSE.txt
Requires-Dist: func-timeout >=4.3.5
Requires-Dist: rfb-config-tool >=0.0.1
Requires-Dist: rfb-logger-tool >=0.0.1
Requires-Dist: rfb-shared-tool >=0.0.1
Requires-Dist: rfb-cycler-datatypes >=0.0.1
Requires-Dist: rfb-driver-db >=0.0.1
Requires-Dist: rfb-driver-epc >=0.0.1
Requires-Dist: rfb-driver-bms >=0.0.1
Requires-Dist: rfb-driver-flow >=0.0.1
Requires-Dist: rfb-driver-ea >=0.0.1
Requires-Dist: rfb-driver-rs >=0.0.1
Requires-Dist: rfb-driver-bk >=0.0.1
